.coveragerc
.testr.conf
COPYING
HACKING
INSTALL
MANIFEST.in
NEWS
README
ci-build
entry_points.ini
integration-tests
setup.cfg
setup.py
lava/__init__.py
lava/commands.py
lava/config.py
lava/parameter.py
lava/device/__init__.py
lava/device/commands.py
lava/device/templates.py
lava/device/tests/__init__.py
lava/device/tests/test_commands.py
lava/device/tests/test_device.py
lava/helper/__init__.py
lava/helper/command.py
lava/helper/dispatcher.py
lava/helper/template.py
lava/helper/tests/__init__.py
lava/helper/tests/helper_test.py
lava/helper/tests/test_command.py
lava/helper/tests/test_dispatcher.py
lava/helper/tests/test_template.py
lava/job/__init__.py
lava/job/commands.py
lava/job/templates.py
lava/job/tests/__init__.py
lava/job/tests/test_commands.py
lava/job/tests/test_job.py
lava/script/__init__.py
lava/script/commands.py
lava/script/tests/__init__.py
lava/script/tests/test_commands.py
lava/script/tests/test_script.py
lava/testdef/__init__.py
lava/testdef/commands.py
lava/testdef/templates.py
lava/testdef/tests/__init__.py
lava/testdef/tests/test_commands.py
lava/tests/__init__.py
lava/tests/test_commands.py
lava/tests/test_config.py
lava/tests/test_parameter.py
lava/tool/__init__.py
lava/tool/command.py
lava/tool/dispatcher.py
lava/tool/errors.py
lava/tool/main.py
lava/tool/commands/__init__.py
lava/tool/commands/help.py
lava_dashboard_tool/__init__.py
lava_dashboard_tool/commands.py
lava_dashboard_tool/main.py
lava_dashboard_tool/tests/__init__.py
lava_dashboard_tool/tests/test_commands.py
lava_scheduler_tool/__init__.py
lava_scheduler_tool/commands.py
lava_tool/__init__.py
lava_tool/authtoken.py
lava_tool/dispatcher.py
lava_tool/interface.py
lava_tool/utils.py
lava_tool.egg-info/PKG-INFO
lava_tool.egg-info/SOURCES.txt
lava_tool.egg-info/dependency_links.txt
lava_tool.egg-info/entry_points.txt
lava_tool.egg-info/namespace_packages.txt
lava_tool.egg-info/requires.txt
lava_tool.egg-info/top_level.txt
lava_tool.egg-info/zip-safe
lava_tool/commands/__init__.py
lava_tool/commands/auth.py
lava_tool/tests/__init__.py
lava_tool/tests/test_auth_commands.py
lava_tool/tests/test_authtoken.py
lava_tool/tests/test_commands.py
lava_tool/tests/test_utils.py
man/Makefile
man/conf.py
man/index.rst
man/lava-tool.rst